trytond/modules/health_ntd_chagas/COPYING
trytond/modules/health_ntd_chagas/README.rst
trytond/modules/health_ntd_chagas/__init__.py
trytond/modules/health_ntd_chagas/data/health_ntd_chagas_sequence.xml
trytond/modules/health_ntd_chagas/data/lab_test_data.xml
trytond/modules/health_ntd_chagas/health_ntd_chagas.py
trytond/modules/health_ntd_chagas/health_ntd_chagas_view.xml
trytond/modules/health_ntd_chagas/locale/ar.po
trytond/modules/health_ntd_chagas/locale/de.po
trytond/modules/health_ntd_chagas/locale/el.po
trytond/modules/health_ntd_chagas/locale/eo.po
trytond/modules/health_ntd_chagas/locale/es.po
trytond/modules/health_ntd_chagas/locale/fr.po
trytond/modules/health_ntd_chagas/locale/health_ntd_chagas.pot
trytond/modules/health_ntd_chagas/locale/it_IT.po
trytond/modules/health_ntd_chagas/locale/ja_JP.po
trytond/modules/health_ntd_chagas/locale/ka.po
trytond/modules/health_ntd_chagas/locale/lo.po
trytond/modules/health_ntd_chagas/locale/pt_BR.po
trytond/modules/health_ntd_chagas/locale/sv.po
trytond/modules/health_ntd_chagas/locale/tr.po
trytond/modules/health_ntd_chagas/locale/uk.po
trytond/modules/health_ntd_chagas/locale/zh_CN.po
trytond/modules/health_ntd_chagas/pyproject.toml
trytond/modules/health_ntd_chagas/sequences.py
trytond/modules/health_ntd_chagas/tests/__init__.py
trytond/modules/health_ntd_chagas/tests/test_health_ntd_chagas.py
trytond/modules/health_ntd_chagas/tryton.cfg
trytond/modules/health_ntd_chagas/view/gnuhealth_chagas_du_survey_form.xml
trytond/modules/health_ntd_chagas/view/gnuhealth_chagas_du_survey_tree.xml
gnuhealth_ntd_chagas-5.0.2.dist-info/METADATA
gnuhealth_ntd_chagas-5.0.2.dist-info/WHEEL
gnuhealth_ntd_chagas-5.0.2.dist-info/licenses/COPYING
gnuhealth_ntd_chagas-5.0.2.dist-info/RECORD
